{
  "slots": [
    [
      "gold_coin",
      99
    ],
    [
      "string",
      3
    ],
    [
      "storm_rune",
      2
    ],
    null,
    [
      "assassin_blade_shard",
      10
    ],
    null,
    null,
    null,
    [
      "gold_coin",
      42
    ],
    [
      "gold_coin",
      99
    ],
    [
      "ember_rune",
      1
    ],
    null,
    [
      "assassin_handle_wrap",
      16
    ],
    null,
    null,
    null,
    [
      "cobweb",
      56
    ],
    null,
    null,
    null,
    null,
    null,
    null,
    null,
    [
      "iron_scrap",
      10
    ],
    [
      "leather_strip",
      2
    ],
    null,
    null,
    null,
    null,
    null,
    null,
    [
      "stone_chip",
      27
    ],
    [
      "legion_helm",
      1
    ],
    null,
    null,
    null,
    null,
    null,
    null
  ],
  "hotbar": [
    [
      "aug_soul_stealer",
      1,
      {
        "infused_rune": "frost_rune"
      }
    ],
    [
      "aug_assassins_grace",
      1,
      {
        "infused_rune": "storm_rune"
      }
    ],
    [
      "aug_soul_stealer",
      1,
      {
        "infused_rune": "ember_rune"
      }
    ],
    null,
    null,
    null,
    [
      "health_potion_large",
      1
    ],
    null
  ],
  "equipment": {
    "weapon": "aug_assassin_shortbow",
    "head": "galea",
    "chest": "legion_cuirass",
    "boots": "caligae",
    "shield": null
  },
  "equipment_meta": {
    "weapon": {
      "infused_rune": "storm_rune"
    }
  },
  "selected_hotbar_index": 0,
  "player_health": 255,
  "current_level": "level8.txt",
  "mob_states": {
    "level1.txt": [],
    "level2.txt": [],
    "level3.txt": [],
    "level4.txt": [],
    "level5.txt": [],
    "level6.txt": [],
    "level7.txt": [],
    "level8.txt": [
      {
        "tile_x": 43,
        "tile_y": 1,
        "health": 230,
        "state": "inactive",
        "mob_type": "ghost"
      },
      {
        "tile_x": 43,
        "tile_y": 2,
        "health": 150,
        "state": "inactive",
        "mob_type": "shadow_assassin"
      }
    ]
  },
  "discovered_recipes": [
    "assassin_shortbow",
    "assassins_grace",
    "woven_cobweb"
  ],
  "player_class_id": "assassin",
  "player_level": 17,
  "player_xp": 250,
  "skill_points": 8,
  "purchased_skill_nodes": [
    "ass_blade",
    "ass_dancer",
    "ass_execution",
    "ass_lethal",
    "ass_nightlord",
    "ass_shadow",
    "ass_survivor",
    "ass_veil"
  ]
}