{
    "weapon_types": {
        "sword": {
            "slots": ["hilt", "blade", "handle"],
            "description": "Swords use a hilt, blade, and handle."
        },
        "dagger": {
            "slots": ["blade", "handle"],
            "description": "Daggers omit a hilt; blade and handle."
        },
        "bow": {
            "slots": ["string", "grip"],
            "description": "Bows use string and grip."
        },
        "staff": {
            "slots": ["focus", "shaft"],
            "description": "Staves use a focus and shaft."
        }
    },
    "recipes": [
        {
            "id": "assassins_grace",
            "display_name": "Assassin's Grace",
            "starts_known": false,
            "discover_on_items": ["assassin_blade_shard", "assassin_handle_wrap"],
            "weapon_type": "dagger",
            "inputs": {
                "blade": "assassin_blade_shard",
                "handle": "assassin_handle_wrap"
            },
            "output": {
                "item_id": "assassins_grace",
                "count": 1
            }
        }
    ]
}
