{
    "statue": {
        "name": "Stone Sentinel",
        "spritesheet": "statue.png",
        "key_checkerboard_grays": true,
        "frame_w": 127,
        "frame_h": 133,
        "sheet_grid_cols": 8,
        "sheet_grid_rows": 4,
        "center_grid_on_sheet": true,
        "idle_frames": 4,
        "walk_frames": 8,
        "attack_frames": 5,
        "death_frames": 6,
        "hp": 200,
        "damage": 50,
        "speed": 12,
        "chase_range_tiles": 6,
        "activation_range_tiles": 5,
        "attack_cooldown_ms": 4000,
        "attack_range_tiles": 1.2,
        "xp": 55,
        "move_delay_ms": 500,
        "slide_duration_ms": 220,
        "attack_anim_speed_ms": 150,
        "anim_speed_ms": 120,
        "hit_frame": 3,
        "drops": [
            {
                "item_id": "gold_coin",
                "count": [
                    2,
                    5
                ],
                "chance": 0.8
            },
            {
                "item_id": "health_potion",
                "count": [
                    1,
                    1
                ],
                "chance": 0.3
            },
            {
                "item_id": "stone_hammer",
                "count": [
                    1,
                    1
                ],
                "chance": 0.15
            },
            {
                "item_id": "galea",
                "count": [
                    1,
                    1
                ],
                "chance": 0.05
            },
            {
                "item_id": "ember_rune",
                "count": [
                    1,
                    1
                ],
                "chance": 0.015
            },
            {
                "item_id": "frost_rune",
                "count": [
                    1,
                    1
                ],
                "chance": 0.012
            },
            {
                "item_id": "storm_rune",
                "count": [
                    1,
                    1
                ],
                "chance": 0.01
            }
        ]
    },
    "shadow_assassin": {
        "name": "Shadow Assassin",
        "spritesheet": "rogue.png",
        "frame_w": 32,
        "frame_h": 32,
        "idle_frames": 10,
        "walk_frames": 10,
        "attack_frames": 10,
        "death_frames": 10,
        "hp": 150,
        "damage": 35,
        "speed": 18,
        "chase_range_tiles": 8,
        "activation_range_tiles": 6,
        "attack_cooldown_ms": 1800,
        "attack_range_tiles": 1.1,
        "xp": 45,
        "move_delay_ms": 300,
        "slide_duration_ms": 170,
        "attack_anim_speed_ms": 95,
        "anim_speed_ms": 95,
        "hit_frame": 3,
        "idle_row": 0,
        "walk_row": 2,
        "heal_row": 1,
        "heal_frames": 10,
        "attack_row": 3,
        "death_row": 4,
        "heal_once_amount": 50,
        "heal_threshold_pct": 0.45,
        "drops": [
            {
                "item_id": "gold_coin",
                "count": [
                    2,
                    6
                ],
                "chance": 0.9
            },
            {
                "item_id": "health_potion",
                "count": [
                    1,
                    2
                ],
                "chance": 0.75
            },
            {
                "item_id": "assassin_blade_shard",
                "count": [
                    1,
                    1
                ],
                "chance": 0.4
            },
            {
                "item_id": "assassin_handle_wrap",
                "count": [
                    1,
                    1
                ],
                "chance": 0.4
            },
            {
                "item_id": "ember_rune",
                "count": [
                    1,
                    1
                ],
                "chance": 0.015
            },
            {
                "item_id": "frost_rune",
                "count": [
                    1,
                    1
                ],
                "chance": 0.012
            },
            {
                "item_id": "storm_rune",
                "count": [
                    1,
                    1
                ],
                "chance": 0.01
            }
        ]
    }
}
